acom_music_box/__init__.py
acom_music_box/conditions.py
acom_music_box/constants.py
acom_music_box/data_output.py
acom_music_box/evolving_conditions.py
acom_music_box/main.py
acom_music_box/model_options.py
acom_music_box/music_box.py
acom_music_box/plot_output.py
acom_music_box/utils.py
acom_music_box/examples/__init__.py
acom_music_box/examples/examples.py
acom_music_box/examples/configs/analytical/initial_conditions.csv
acom_music_box/examples/configs/analytical/my_config.json
acom_music_box/examples/configs/analytical/camp_data/config.json
acom_music_box/examples/configs/analytical/camp_data/reactions.json
acom_music_box/examples/configs/analytical/camp_data/species.json
acom_music_box/examples/configs/carbon_bond_5/initial_concentrations.csv
acom_music_box/examples/configs/carbon_bond_5/initial_reaction_rates.csv
acom_music_box/examples/configs/carbon_bond_5/my_config.json
acom_music_box/examples/configs/carbon_bond_5/camp_data/config.json
acom_music_box/examples/configs/carbon_bond_5/camp_data/reactions.json
acom_music_box/examples/configs/carbon_bond_5/camp_data/species.json
acom_music_box/examples/configs/carbon_bond_5/camp_data/tolerance.json
acom_music_box/examples/configs/chapman/conditions_Boulder.csv
acom_music_box/examples/configs/chapman/initial_concentrations.csv
acom_music_box/examples/configs/chapman/my_config.json
acom_music_box/examples/configs/chapman/camp_data/config.json
acom_music_box/examples/configs/chapman/camp_data/reactions.json
acom_music_box/examples/configs/chapman/camp_data/species.json
acom_music_box/examples/configs/chapman/camp_data/tolerance.json
acom_music_box/examples/configs/flow_tube/initial_concentrations.csv
acom_music_box/examples/configs/flow_tube/initial_reaction_rates.csv
acom_music_box/examples/configs/flow_tube/my_config.json
acom_music_box/examples/configs/flow_tube/camp_data/config.json
acom_music_box/examples/configs/flow_tube/camp_data/reactions.json
acom_music_box-2.11.0.dist-info/entry_points.txt
acom_music_box-2.11.0.dist-info/licenses/LICENSE
acom_music_box-2.11.0.dist-info/WHEEL
acom_music_box-2.11.0.dist-info/METADATA
acom_music_box-2.11.0.dist-info/RECORD
