Metadata-Version: 2.4
Name: acom_music_box
Version: 2.11.0
Summary: An atmospheric chemistry box model. Powered by MUSICA.
Author: Evan De la Garza, Walker Drury, Alexander Garza, Brendan Fattig, Montek Thind, Aditya Kiran, Aidan Winney, Angela Pak
Author-email: Matthew Dawson <mattdawson@ucar.edu>, Kyle Shores <kshores@ucar.edu>, Andrew Conley <aconley@ucar.edu>, Carl Drews <drews@ucar.edu>
Maintainer-email: ACOM MUSICA Developers <musica-support@ucar.edu>
Requires-Python: >=3.10
Classifier: License :: OSI Approved :: Apache Software License
License-File: LICENSE
Requires-Dist: colorlog>=6.7.0
Requires-Dist: matplotlib>=3.6.0
Requires-Dist: mplcursors>=0.3
Requires-Dist: musica>=0.14.0
Requires-Dist: netcdf4>=1.6.0
Requires-Dist: numpy>=2.0.0
Requires-Dist: pandas>=2.2.0
Requires-Dist: tqdm>=4.64.0
Requires-Dist: typing_extensions>=4.4.0
Requires-Dist: xarray>=2022.3.0
Requires-Dist: pathvalidate>=3.3.0
Requires-Dist: pytest>=7.0.0 ; extra == "dev"
Requires-Dist: pytest-mock>=3.15.0 ; extra == "dev"
Requires-Dist: pytest-cov>=7.0.0 ; extra == "dev"
Requires-Dist: musica[gpu]==0.14.0 ; extra == "gpu"
Project-URL: Home, https://github.com/NCAR/music-box
Provides-Extra: dev
Provides-Extra: gpu
